retrofy/__init__.py
retrofy/_converters.py
retrofy/_meta_hook_converter.py
retrofy/_pep517_hooks.py
retrofy/_version.py
retrofy/_transformations/__init__.py
retrofy/_transformations/dataclass.py
retrofy/_transformations/import_utils.py
retrofy/_transformations/match_statement.py
retrofy/_transformations/type_alias.py
retrofy/_transformations/walrus.py
retrofy/tests/__init__.py
retrofy/tests/test__converters.py
retrofy/tests/test_integration_match.py
retrofy/tests/test_retrofy.py
retrofy/tests/_transformations/__init__.py
retrofy/tests/_transformations/test__type_alias.py
retrofy/tests/_transformations/test__walrus.py
retrofy/tests/_transformations/test_dataclasses.py
retrofy/tests/_transformations/test_future_imports.py
retrofy/tests/_transformations/test_match_statement.py
retrofy-0.2.1.dist-info/METADATA
retrofy-0.2.1.dist-info/WHEEL
retrofy-0.2.1.dist-info/entry_points.txt
retrofy-0.2.1.dist-info/top_level.txt
retrofy-0.2.1.dist-info/RECORD
