Metadata-Version: 2.4
Name: retrofy
Version: 0.2.1
Summary: A tool to convert modern Python code to less modern Python versions
Author-email: Phil Elson <pelson.pub@gmail.com>
License-Expression: Apache-2.0
Project-URL: Homepage, https://github.com/pelson/retrofy
Classifier: Programming Language :: Python :: 3
Classifier: Operating System :: OS Independent
Requires-Python: >=3.9
Requires-Dist: libcst
Requires-Dist: setuptools-ext
Provides-Extra: test
Requires-Dist: pytest; extra == "test"
